tree_sitter_bicep/__init__.pyi
tree_sitter_bicep/binding.c
tree_sitter_bicep/__init__.py
tree_sitter_bicep/py.typed
tree_sitter_bicep/_binding.abi3.so
tree_sitter_bicep/queries/locals.scm
tree_sitter_bicep/queries/indents.scm
tree_sitter_bicep/queries/highlights.scm
tree_sitter_bicep/queries/folds.scm
tree_sitter_bicep/queries/injections.scm
tree_sitter_bicep-1.1.0.dist-info/RECORD
tree_sitter_bicep-1.1.0.dist-info/LICENSE
tree_sitter_bicep-1.1.0.dist-info/WHEEL
tree_sitter_bicep-1.1.0.dist-info/top_level.txt
tree_sitter_bicep-1.1.0.dist-info/METADATA
